LICENSE.txt
MANIFEST.in
README.rst
setup.py
ezIBpy.egg-info/PKG-INFO
ezIBpy.egg-info/SOURCES.txt
ezIBpy.egg-info/dependency_links.txt
ezIBpy.egg-info/entry_points.txt
ezIBpy.egg-info/requires.txt
ezIBpy.egg-info/top_level.txt
ezibpy/__init__.py
ezibpy/ezibpy.py
ezibpy/utils.py