Metadata-Version: 1.1
Name: ezIBpy
Version: 1.12.70
Summary: a Pythonic Client for Interactive Brokers API
Home-page: https://github.com/ranaroussi/ezibpy
Author: Ran Aroussi
Author-email: ran@aroussi.com
License: Apache Software License
Keywords: ezibpy,interactive brokers,tws,ibgw,ibpy
Platform: any
Classifier: License :: OSI Approved :: Apache Software License
Classifier: Development Status :: 5 - Production/Stable
Classifier: Operating System :: OS Independent
Classifier: Intended Audience :: Developers
Classifier: Topic :: Office/Business :: Financial
Classifier: Topic :: Office/Business :: Financial :: Investment
Classifier: Topic :: Scientific/Engineering :: Interface Engine/Protocol Translator
Classifier: Topic :: Software Development :: Libraries
Classifier: Topic :: Software Development :: Libraries :: Python Modules
Classifier: Programming Language :: Python :: 3.5
Classifier: Programming Language :: Python :: 3.6
Classifier: Programming Language :: Python :: 3.7
